tomo/__init__.py
tomo/constants.py
tomo/icon.png
tomo/objects.py
tomo/protocols.conf
tomo/utils.py
tomo/wizards.py
tomo/convert/__init__.py
tomo/convert/convert.py
tomo/convert/mdoc.py
tomo/protocols/__init__.py
tomo/protocols/protocol_assignTransformationTS.py
tomo/protocols/protocol_base.py
tomo/protocols/protocol_compose_TS.py
tomo/protocols/protocol_correct_tilt_offset.py
tomo/protocols/protocol_export_coords.py
tomo/protocols/protocol_extract_coordinates.py
tomo/protocols/protocol_import_coordinates.py
tomo/protocols/protocol_import_coordinates_from_scipion.py
tomo/protocols/protocol_import_ctf.py
tomo/protocols/protocol_import_subtomograms.py
tomo/protocols/protocol_import_tomograms.py
tomo/protocols/protocol_import_tomomasks.py
tomo/protocols/protocol_invert_tilt_angles.py
tomo/protocols/protocol_mask_coordinates.py
tomo/protocols/protocol_mesh_from_segmentation.py
tomo/protocols/protocol_misalignTS.py
tomo/protocols/protocol_particles_to_subtomograms.py
tomo/protocols/protocol_project_coordinates.py
tomo/protocols/protocol_split_evenodd_subtomos.py
tomo/protocols/protocol_tomo_apply_tomomask.py
tomo/protocols/protocol_tomo_to_mics.py
tomo/protocols/protocol_ts_base.py
tomo/protocols/protocol_ts_consensus_alignment.py
tomo/protocols/protocol_ts_convert_coords3d.py
tomo/protocols/protocol_ts_correct_motion.py
tomo/protocols/protocol_ts_estimate_ctf.py
tomo/protocols/protocol_ts_from_tomograms.py
tomo/protocols/protocol_ts_import.py
tomo/protocols/protocol_ts_import_coordinates.py
tomo/protocols/deprecated/__init__.py
tomo/protocols/deprecated/protocol_alignment_assign.py
tomo/protocols/deprecated/protocol_assign_tomo2subtomo.py
tomo/protocols/deprecated/protocol_assign_tomo2tomoMask.py
tomo/protocols/deprecated/protocol_consensus_classes_subtomo.py
tomo/protocols/deprecated/protocol_ctf_consensus.py
tomo/protocols/deprecated/protocol_ctf_validate.py
tomo/protocols/deprecated/protocol_fit_ellipsoid.py
tomo/protocols/deprecated/protocol_landmark_to_2d.py
scipion_em_tomo-3.11.4.dist-info/LICENSE
scipion_em_tomo-3.11.4.dist-info/METADATA
scipion_em_tomo-3.11.4.dist-info/WHEEL
scipion_em_tomo-3.11.4.dist-info/entry_points.txt
scipion_em_tomo-3.11.4.dist-info/top_level.txt
scipion_em_tomo-3.11.4.dist-info/RECORD
