Metadata-Version: 2.1
Name: scipion-em-tomo
Version: 3.11.4
Summary: Plugin to use tomo within the Scipion framework
Author-email: Scipion Team <scipion@cnb.csic.es>
License: GNU General Public License v3 (GPLv3)
Project-URL: Homepage, https://github.com/scipion-em/scipion-em-tomo
Project-URL: Issues, https://github.com/scipion-em/scipion-em-tomo/issues
Keywords: scipion,cryoem,cryoet,imageprocessing,scipion-3.0
Classifier: Development Status :: 4 - Beta
Classifier: License :: OSI Approved :: GNU General Public License v3 (GPLv3)
Classifier: Programming Language :: Python :: 3
Requires-Python: >=3.8
License-File: LICENSE
Requires-Dist: mrcfile<=1.4.3,>=1.4.0
Requires-Dist: scipion-em>=3.9.1
